garm_rate_limiter/__init__.py
garm_rate_limiter/config.py
garm_rate_limiter/constants.py
garm_rate_limiter/exceptions.py
garm_rate_limiter/limiter.py
garm_rate_limiter-0.1.3.dist-info/LICENSE
garm_rate_limiter-0.1.3.dist-info/METADATA
garm_rate_limiter-0.1.3.dist-info/WHEEL
garm_rate_limiter-0.1.3.dist-info/top_level.txt
garm_rate_limiter-0.1.3.dist-info/RECORD
